lyzr_tool_call/__init__.py
lyzr_tool_call/server.py
lyzr_mcp_tool_call-0.1.7.dist-info/METADATA
lyzr_mcp_tool_call-0.1.7.dist-info/WHEEL
lyzr_mcp_tool_call-0.1.7.dist-info/entry_points.txt
lyzr_mcp_tool_call-0.1.7.dist-info/top_level.txt
lyzr_mcp_tool_call-0.1.7.dist-info/RECORD
