Metadata-Version: 2.4
Name: lyzr-mcp-tool-call
Version: 0.1.7
Summary: An MCP server for calling Lyzr agents
Author-email: Rasswanth <rasswanth@lyzr.ai>
Requires-Python: >=3.10
Requires-Dist: fastmcp>=2.4.0
Requires-Dist: twine>=6.1.0
